LICENSE
MANIFEST.in
README.rst
requirements.txt
setup.py
python_template/__init__.py
python_template/newmodule.py
python_template/templates/.gitignore
python_template/templates/LICENSE
python_template/templates/README.rst_tmpl
python_template/templates/requirements.txt
python_template/templates/setup.cfg_tmpl
python_template/templates/setup.py_tmpl
python_template/templates/tox.ini
python_template/templates/+package+/+package+.py_tmpl
python_template/templates/+package+/__init__.py_tmpl
python_template/templates/scripts/dummy.py_tmpl
python_template/templates/tests/test_basic.py_tmpl
standard.paster.egg-info/PKG-INFO
standard.paster.egg-info/SOURCES.txt
standard.paster.egg-info/dependency_links.txt
standard.paster.egg-info/entry_points.txt
standard.paster.egg-info/requires.txt
standard.paster.egg-info/top_level.txt
standard.paster.egg-info/version.txt
standard.paster.egg-info/version_full.txt
standard.paster.egg-info/zip-safe