Metadata-Version: 1.1
Name: standard.paster
Version: 1.0
Summary: Quickly create a standard Python module layout
Home-page: https://github.com/jonEbird/standard-paster
Author: Jon Miller
Author-email: jonEbird@gmail.com
License: Apache
Keywords: paster bootstrap
Platform: UNKNOWN
Classifier: Development Status :: 5 - Production/Stable
Classifier: Environment :: Console
Classifier: Environment :: Plugins
Classifier: Framework :: Paste
Classifier: Intended Audience :: Developers
Classifier: Operating System :: OS Independent
Classifier: Programming Language :: Python
Classifier: Topic :: Software Development :: Code Generators
